oimdp/__init__.py
oimdp/parser.py
oimdp/structures.py
oimdp/tags.py
oimdp-1.3.0.dist-info/LICENSE
oimdp-1.3.0.dist-info/METADATA
oimdp-1.3.0.dist-info/WHEEL
oimdp-1.3.0.dist-info/top_level.txt
oimdp-1.3.0.dist-info/RECORD
