Metadata-Version: 2.1
Name: oimdp
Version: 1.3.0
Summary: OpenITI mARkdown Parser
Home-page: http://github.com/OpenITI/oimdp
Author: Raff Viglianti
Author-email: rviglian@umd.edu
License: UNKNOWN
Platform: UNKNOWN
Requires-Python: >=3.8
License-File: LICENSE
